ZhihuWendaYuangongLizhiBaofuGongsiDaozhiGongsiZhongdasunshiKuadiaoDaobiShiShenmeTiyan/README.md
ZhihuWendaYuangongLizhiBaofuGongsiDaozhiGongsiZhongdasunshiKuadiaoDaobiShiShenmeTiyan/__init__.py
ZhihuWendaYuangongLizhiBaofuGongsiDaozhiGongsiZhongdasunshiKuadiaoDaobiShiShenmeTiyan/__main__.py
ZhihuWendaYuangongLizhiBaofuGongsiDaozhiGongsiZhongdasunshiKuadiaoDaobiShiShenmeTiyan/file.epub
ZhihuWendaYuangongLizhiBaofuGongsiDaozhiGongsiZhongdasunshiKuadiaoDaobiShiShenmeTiyan/index.html
ZhihuWendaYuangongLizhiBaofuGongsiDaozhiGongsiZhongdasunshiKuadiaoDaobiShiShenmeTiyan/css/__init__.py
ZhihuWendaYuangongLizhiBaofuGongsiDaozhiGongsiZhongdasunshiKuadiaoDaobiShiShenmeTiyan/css/annotations.css
ZhihuWendaYuangongLizhiBaofuGongsiDaozhiGongsiZhongdasunshiKuadiaoDaobiShiShenmeTiyan/css/main.css
ZhihuWendaYuangongLizhiBaofuGongsiDaozhiGongsiZhongdasunshiKuadiaoDaobiShiShenmeTiyan/css/normalize.css
ZhihuWendaYuangongLizhiBaofuGongsiDaozhiGongsiZhongdasunshiKuadiaoDaobiShiShenmeTiyan/css/popup.css
ZhihuWendaYuangongLizhiBaofuGongsiDaozhiGongsiZhongdasunshiKuadiaoDaobiShiShenmeTiyan/font/__init__.py
ZhihuWendaYuangongLizhiBaofuGongsiDaozhiGongsiZhongdasunshiKuadiaoDaobiShiShenmeTiyan/font/fontello.eot
ZhihuWendaYuangongLizhiBaofuGongsiDaozhiGongsiZhongdasunshiKuadiaoDaobiShiShenmeTiyan/font/fontello.svg
ZhihuWendaYuangongLizhiBaofuGongsiDaozhiGongsiZhongdasunshiKuadiaoDaobiShiShenmeTiyan/font/fontello.ttf
ZhihuWendaYuangongLizhiBaofuGongsiDaozhiGongsiZhongdasunshiKuadiaoDaobiShiShenmeTiyan/font/fontello.woff
ZhihuWendaYuangongLizhiBaofuGongsiDaozhiGongsiZhongdasunshiKuadiaoDaobiShiShenmeTiyan/img/__init__.py
ZhihuWendaYuangongLizhiBaofuGongsiDaozhiGongsiZhongdasunshiKuadiaoDaobiShiShenmeTiyan/img/annotator-glyph-sprite.png
ZhihuWendaYuangongLizhiBaofuGongsiDaozhiGongsiZhongdasunshiKuadiaoDaobiShiShenmeTiyan/img/annotator-icon-sprite.png
ZhihuWendaYuangongLizhiBaofuGongsiDaozhiGongsiZhongdasunshiKuadiaoDaobiShiShenmeTiyan/img/apple-touch-icon.png
zhihu_wenda_yuangong_lizhi_baofu_gongsi_daozhi_gongsi_zhongdasunshi_kuadiao_daobi_shi_shenme_tiyan-2024.3.5.0.dist-info/METADATA
zhihu_wenda_yuangong_lizhi_baofu_gongsi_daozhi_gongsi_zhongdasunshi_kuadiao_daobi_shi_shenme_tiyan-2024.3.5.0.dist-info/WHEEL
zhihu_wenda_yuangong_lizhi_baofu_gongsi_daozhi_gongsi_zhongdasunshi_kuadiao_daobi_shi_shenme_tiyan-2024.3.5.0.dist-info/entry_points.txt
zhihu_wenda_yuangong_lizhi_baofu_gongsi_daozhi_gongsi_zhongdasunshi_kuadiao_daobi_shi_shenme_tiyan-2024.3.5.0.dist-info/top_level.txt
zhihu_wenda_yuangong_lizhi_baofu_gongsi_daozhi_gongsi_zhongdasunshi_kuadiao_daobi_shi_shenme_tiyan-2024.3.5.0.dist-info/RECORD
