Metadata-Version: 2.1
Name: zhihu-wenda-yuangong-lizhi-baofu-gongsi-daozhi-gongsi-zhongdasunshi-kuadiao-daobi-shi-shenme-tiyan
Version: 2024.3.5.0
Summary: 知乎问答：员工离职，报复公司导致公司重大损失-垮掉-倒闭是什么体验？
Home-page: https://github.com/apachecn/zhihu-wenda-yuangong-lizhi-baofu-gongsi-daozhi-gongsi-zhongdasunshi-kuadiao-daobi-shi-shenme-tiyan
Author: ApacheCN
Author-email: apachecn@163.com
License: UNKNOWN
Platform: UNKNOWN
Classifier: Development Status :: 4 - Beta
Classifier: Environment :: Console
Classifier: Intended Audience :: Developers
Classifier: Intended Audience :: End Users/Desktop
Classifier: License :: Other/Proprietary License
Classifier: Natural Language :: Chinese (Simplified)
Classifier: Natural Language :: English
Classifier: Operating System :: OS Independent
Classifier: Programming Language :: Python :: 3
Classifier: Programming Language :: Python :: 3 :: Only
Classifier: Programming Language :: Python :: 3.6
Classifier: Programming Language :: Python :: 3.7
Classifier: Topic :: Text Processing :: Markup :: Markdown
Classifier: Topic :: Text Processing :: Markup :: HTML
Classifier: Topic :: Internet :: WWW/HTTP
Classifier: Topic :: Software Development :: Documentation
Classifier: Topic :: Documentation
Requires-Python: >=3.6
